inventree_stl_viewer-0.1.0.dist-info/licenses/LICENSE
stl_viewer/__init__.py
stl_viewer/core.py
stl_viewer/static/Panel.js
stl_viewer/static/Panel.js.map
stl_viewer/static/.vite/manifest.json
inventree_stl_viewer-0.1.0.dist-info/METADATA
inventree_stl_viewer-0.1.0.dist-info/WHEEL
inventree_stl_viewer-0.1.0.dist-info/entry_points.txt
inventree_stl_viewer-0.1.0.dist-info/top_level.txt
inventree_stl_viewer-0.1.0.dist-info/RECORD
